Metadata-Version: 2.1
Name: pyImpossibleObf
Version: 6.7.1
Summary: Hashy is the best python obfuscator
Home-page: UNKNOWN
Author: 0xSxZ
Author-email: yazdraw@gmail.com
License: MIT
Keywords: obfuscator
Platform: UNKNOWN
